yk_bit_api_models/__init__.py
yk_bit_api_models/authenticate_response.py
yk_bit_api_models/ble_connection_request.py
yk_bit_api_models/camera_id_request.py
yk_bit_api_models/camera_status.py
yk_bit_api_models/capture_request.py
yk_bit_api_models/capture_response.py
yk_bit_api_models/hardware_reset_response.py
yk_bit_api_models/status_response.py
yk_bit_api_models/verify_images_request.py
yk_bit_api_models/verify_images_response.py
yk_bit_api_models/verify_request.py
yk_bit_api_models/verify_response.py
yk_bit_api_model-1.3.4.post0.dist-info/LICENSE
yk_bit_api_model-1.3.4.post0.dist-info/METADATA
yk_bit_api_model-1.3.4.post0.dist-info/WHEEL
yk_bit_api_model-1.3.4.post0.dist-info/top_level.txt
yk_bit_api_model-1.3.4.post0.dist-info/RECORD
