Metadata-Version: 2.1
Name: yk-bit-api-model
Version: 1.3.4.post0
Summary: Youverse Biometric In Things API data model package.
Home-page: https://www.youverse.id
Author: Youverse
Author-email: tech@youverse.id
License: MIT
Platform: UNKNOWN
Classifier: Programming Language :: Python :: 3
Classifier: License :: OSI Approved :: MIT License
Classifier: Operating System :: OS Independent
Requires-Python: >=3.7
Requires-Dist: yk-utils (<2,>=1.1.4)
